LICENSE
MANIFEST.in
README.rst
setup.py
tox.ini
modeldocs/__init__.py
modeldocs/document.py
modeldocs.egg-info/PKG-INFO
modeldocs.egg-info/SOURCES.txt
modeldocs.egg-info/dependency_links.txt
modeldocs.egg-info/entry_points.txt
modeldocs.egg-info/top_level.txt
modeldocs/.ropeproject/config.py
modeldocs/templates/index.html
modeldocs/templates/main.js
modeldocs/templates/css/style.css
modeldocs/templates/img/favicon.ico
modeldocs/templates/locales/ca.js
modeldocs/templates/locales/de.js
modeldocs/templates/locales/es.js
modeldocs/templates/locales/fr.js
modeldocs/templates/locales/it.js
modeldocs/templates/locales/locale.js
modeldocs/templates/locales/nl.js
modeldocs/templates/locales/pl.js
modeldocs/templates/locales/pt_br.js
modeldocs/templates/locales/ro.js
modeldocs/templates/locales/ru.js
modeldocs/templates/locales/zh.js
modeldocs/templates/locales/zh_cn.js
modeldocs/templates/utils/handlebars_helper.js
modeldocs/templates/utils/send_sample_request.js
modeldocs/templates/vendor/bootstrap.min.css
modeldocs/templates/vendor/bootstrap.min.js
modeldocs/templates/vendor/diff_match_patch.min.js
modeldocs/templates/vendor/handlebars.min.js
modeldocs/templates/vendor/jquery.min.js
modeldocs/templates/vendor/list.min.js
modeldocs/templates/vendor/lodash.custom.min.js
modeldocs/templates/vendor/polyfill.js
modeldocs/templates/vendor/prettify.css
modeldocs/templates/vendor/require.min.js
modeldocs/templates/vendor/semver.min.js
modeldocs/templates/vendor/webfontloader.js
modeldocs/templates/vendor/path-to-regexp/LICENSE
modeldocs/templates/vendor/path-to-regexp/index.js
modeldocs/templates/vendor/prettify/lang-Splus.js
modeldocs/templates/vendor/prettify/lang-aea.js
modeldocs/templates/vendor/prettify/lang-agc.js
modeldocs/templates/vendor/prettify/lang-apollo.js
modeldocs/templates/vendor/prettify/lang-basic.js
modeldocs/templates/vendor/prettify/lang-cbm.js
modeldocs/templates/vendor/prettify/lang-cl.js
modeldocs/templates/vendor/prettify/lang-clj.js
modeldocs/templates/vendor/prettify/lang-css.js
modeldocs/templates/vendor/prettify/lang-dart.js
modeldocs/templates/vendor/prettify/lang-el.js
