Metadata-Version: 1.1
Name: modeldocs
Version: 0.1.3
Summary: Documentation generator for your model subclasses.
Home-page: https://github.com/johannestaas/modeldocs
Author: Johan Nestaas
Author-email: johannestaas@gmail.com
License: MIT
Platform: UNKNOWN
Classifier: Development Status :: 3 - Alpha
Classifier: License :: OSI Approved :: MIT License
Classifier: Environment :: Console
Classifier: Environment :: X11 Applications :: Qt
Classifier: Environment :: MacOS X
Classifier: Environment :: Win32 (MS Windows)
Classifier: Operating System :: POSIX
Classifier: Operating System :: MacOS :: MacOS X
Classifier: Operating System :: Microsoft :: Windows
Classifier: Programming Language :: Python
